{
	"region": {
		"Currituck County": {
			"storm_surge|1": [37],
			"storm_surge|2": [38],
			"storm_surge|3": [39],
			"storm_surge|4": [40],
			"storm_surge|5": [41],
			
			"shallow_coastal_flooding": [26],
			
			"sea_level_rise|current|low": [21,29],
			"sea_level_rise|current|medium": [21,29],
			"sea_level_rise|current|high": [21,29],
			"sea_level_rise|2030|low": [13,29],
			"sea_level_rise|2030|medium": [14,29],
			"sea_level_rise|2030|high": [12,29],
			"sea_level_rise|2060|low": [16,29],
			"sea_level_rise|2060|medium": [17,29],
			"sea_level_rise|2060|high": [15,29],
			"sea_level_rise|2100|low": [19,29],
			"sea_level_rise|2100|medium": [20,29],
			"sea_level_rise|2100|high": [18,29],
			
			"fema": [23]
		
		},
		"Dare County": {
			"storm_surge|1": [31],
			"storm_surge|2": [32],
			"storm_surge|3": [33],
			"storm_surge|4": [34],
			"storm_surge|5": [35],
			
			"shallow_coastal_flooding": [27],
			
			"sea_level_rise|current|low": [10,29],
			"sea_level_rise|current|medium": [10,29],
			"sea_level_rise|current|high": [10,29],
			"sea_level_rise|2030|low": [2,29],
			"sea_level_rise|2030|medium": [3,29],
			"sea_level_rise|2030|high": [1,29],
			"sea_level_rise|2060|low": [5,29],
			"sea_level_rise|2060|medium": [6,29],
			"sea_level_rise|2060|high": [4,29],
			"sea_level_rise|2100|low": [8,29],
			"sea_level_rise|2100|medium": [9,29],
			"sea_level_rise|2100|high": [7,29],
			
			"fema": [24]
		}
	}
}